morphotreeviz-0.0.4.dist-info/licenses/LICENSE
mtviz/__init__.py
mtviz/bundle.py
mtviz/console.py
mtviz/helpers.py
mtviz/image.py
mtviz/levelsets.py
mtviz/tree.py
mtviz/js/flood.js
morphotreeviz-0.0.4.dist-info/METADATA
morphotreeviz-0.0.4.dist-info/WHEEL
morphotreeviz-0.0.4.dist-info/top_level.txt
morphotreeviz-0.0.4.dist-info/RECORD
