Metadata-Version: 2.4
Name: MorphoTreeViz
Version: 0.0.4
Summary: Morphological Trees Visualization
Author: Wonder Alexandre Luz Alves
License:                     GNU GENERAL PUBLIC LICENSE
Keywords: tree,morphological,print,bokeh,visualization
Classifier: Programming Language :: Python :: 3
Classifier: License :: OSI Approved :: MIT License
Classifier: Operating System :: OS Independent
Requires-Python: >=3.8
License-File: LICENSE
Requires-Dist: numpy>=1.21
Requires-Dist: bokeh>=3.1
Dynamic: license-file
